buildingenergy/__init__.py
buildingenergy/dynprog.py
buildingenergy/linreg.py
buildingenergy/measurements.py
buildingenergy/model.py
buildingenergy/openweather.py
buildingenergy/solar.py
buildingenergy/solarbuilding.py
buildingenergy/thermics.py
buildingenergy/timemg.py
h358/__init__.py
h358/h358dynprog.py
h358/h358linreg.py
h358/h358measurements.py
h358/h358model.py
h358/h358parameters.py
h358/h358simulator.py
h358/h358sliding.py
h358/h358solar.py
h358/h358solarbuilding.py
h358/h358statmodel.py
h358/h358weather.py
buildingenergy-0.0.3.dist-info/LICENSE
buildingenergy-0.0.3.dist-info/METADATA
buildingenergy-0.0.3.dist-info/WHEEL
buildingenergy-0.0.3.dist-info/top_level.txt
buildingenergy-0.0.3.dist-info/RECORD
