Metadata-Version: 2.1
Name: buildingenergy
Version: 0.0.3
Summary: Tools for energy management in buildings
Home-page: https://gricad-gitlab.univ-grenoble-alpes.fr/ploixs/h358
Author: Stephane Ploix
Author-email: stephane.ploix@grenoble-inp.fr
License: UNKNOWN
Platform: UNKNOWN
Classifier: Programming Language :: Python :: 3
Classifier: License :: OSI Approved :: MIT License
Classifier: Operating System :: OS Independent
Requires-Python: >=3.6
License-File: LICENSE
